aiopylgtv/__init__.py
aiopylgtv/buttons.py
aiopylgtv/cal_commands.py
aiopylgtv/constants.py
aiopylgtv/endpoints.py
aiopylgtv/handshake.py
aiopylgtv/lut_tools.py
aiopylgtv/utils.py
aiopylgtv/webos_client.py
aiopylgtv-0.4.1.dist-info/LICENSE.txt
aiopylgtv-0.4.1.dist-info/METADATA
aiopylgtv-0.4.1.dist-info/WHEEL
aiopylgtv-0.4.1.dist-info/entry_points.txt
aiopylgtv-0.4.1.dist-info/top_level.txt
aiopylgtv-0.4.1.dist-info/zip-safe
aiopylgtv-0.4.1.dist-info/RECORD
