Metadata-Version: 2.1
Name: aiopylgtv
Version: 0.4.1
Summary: Library to control webOS based LG TV devices.
Home-page: https://github.com/bendavid/aiopylgtv
Author: Josh Bendavid
Author-email: joshbendavid@gmail.com
License: UNKNOWN
Keywords: webos,tv
Platform: UNKNOWN
Requires-Python: >=3.7
Requires-Dist: websockets (>=8.1)
Requires-Dist: numpy (>=1.17.0)
Requires-Dist: sqlitedict
